qrules/__init__.py
qrules/_attrs.py
qrules/_implementers.py
qrules/additional_definitions.yml
qrules/argument_handling.py
qrules/combinatorics.py
qrules/conservation_rules.py
qrules/particle-validation.json
qrules/particle.py
qrules/py.typed
qrules/quantum_numbers.py
qrules/settings.py
qrules/solving.py
qrules/system_control.py
qrules/topology.py
qrules/transition.py
qrules/version.py
qrules/io/__init__.py
qrules/io/_dict.py
qrules/io/_dot.py
qrules-0.10.6.dist-info/licenses/LICENSE
qrules-0.10.6.dist-info/METADATA
qrules-0.10.6.dist-info/WHEEL
qrules-0.10.6.dist-info/top_level.txt
qrules-0.10.6.dist-info/RECORD
