Metadata-Version: 2.4
Name: qrules
Version: 0.10.6
Summary: Rule-based particle reaction problem solver on a quantum number level
Author-email: Common Partial Wave Analysis <compwa-admin@ep1.rub.de>
Maintainer-email: compwa-admin@ep1.rub.de
License:                                  Apache License
Project-URL: Changelog, https://github.com/ComPWA/qrules/releases
Project-URL: Documentation, https://qrules.rtfd.io
Project-URL: Source, https://github.com/ComPWA/qrules
Project-URL: Tracker, https://github.com/ComPWA/qrules/issues
Keywords: HEP,PWA,amplitude analysis,partial wave analysis,particle physics,particles,physics
Classifier: Development Status :: 4 - Beta
Classifier: Intended Audience :: Developers
Classifier: Intended Audience :: Education
Classifier: Intended Audience :: Science/Research
Classifier: License :: OSI Approved :: Apache Software License
Classifier: Natural Language :: English
Classifier: Operating System :: OS Independent
Classifier: Programming Language :: Python :: 3.10
Classifier: Programming Language :: Python :: 3.11
Classifier: Programming Language :: Python :: 3.12
Classifier: Programming Language :: Python :: 3.13
Classifier: Programming Language :: Python :: 3.14
Classifier: Programming Language :: Python
Classifier: Topic :: Scientific/Engineering :: Physics
Classifier: Topic :: Scientific/Engineering
Classifier: Typing :: Typed
Requires-Python: >=3.10
License-File: LICENSE
Requires-Dist: PyYAML
Requires-Dist: attrs>=20.1.0
Requires-Dist: frozendict
Requires-Dist: jsonschema
Requires-Dist: particle
Requires-Dist: python-constraint
Requires-Dist: tqdm>=4.24.0
Provides-Extra: viz
Requires-Dist: graphviz; extra == "viz"
Dynamic: license-file
